awsmeta/__init__.py
awsmeta/cli.py
awsmeta/metadata.py
awsmeta-0.5.1.data/data/etc/bash_completion.d/awsmeta
awsmeta-0.5.1.dist-info/DESCRIPTION.rst
awsmeta-0.5.1.dist-info/entry_points.txt
awsmeta-0.5.1.dist-info/METADATA
awsmeta-0.5.1.dist-info/metadata.json
awsmeta-0.5.1.dist-info/RECORD
awsmeta-0.5.1.dist-info/top_level.txt
awsmeta-0.5.1.dist-info/WHEEL
