Metadata-Version: 2.0
Name: awsmeta
Version: 0.5.1
Summary: A tool for querying the AWS metadata service from the CLI
Home-page: https://github.com/slank/awsmeta
Author: Matthew Wedgwood
Author-email: mw@rmn.com
License: MIT
Platform: UNKNOWN
Classifier: Development Status :: 5 - Production/Stable
Classifier: Intended Audience :: System Administrators
Classifier: License :: OSI Approved :: MIT License
Classifier: Operating System :: OS Independent
Classifier: Topic :: Internet
Classifier: Programming Language :: Python :: 2
Classifier: Programming Language :: Python :: 3
Classifier: Topic :: Internet
